<?xml version="1.0" encoding="utf-8" standalone="no"?>
<xDocument>
    <!--自訂報告系統代碼-->
    <reportCode>1003</reportCode>
    <!--自訂報告系統版本-->
    <reportVersion>3</reportVersion>
    <!--報告名稱-->
    <title>門診病歷單</title>
    <!--參考號碼-->
    <orderNo>1234567810030003</orderNo>
    <!--單號-->
    <referNo>12345678</referNo>
    <!--病歷號-->
    <patientId>123456</patientId>
    <!--身分證號-->
    <patientIdNumber>Z123456789</patientIdNumber>
    <!--病患姓名-->
    <patientName>陳小美</patientName>
    <!--病患生日-->
    <patientBirth>20240701</patientBirth>
    <!--病患性別-->
    <patientSex>F</patientSex>
    <!--病患來源-->
    <patientSource>I</patientSource>
    <!--醫療院所代號-->
    <hospitalId>1A0</hospitalId>
    <!--醫療院所名稱-->
    <hospitalName>高雄榮民總醫院</hospitalName>
    <!--報告醫師-->
    <reportAuthor>
        <!--報告醫師代碼-->
        <reportDoctorId>admin</reportDoctorId>
        <!--報告醫師姓名-->
        <reportDoctorName>admin</reportDoctorName>
    </reportAuthor>
    <!--報告醫師-->
    <reportAuthor>
        <!--報告醫師代碼-->
        <reportDoctorId>exentric</reportDoctorId>
        <!--報告醫師姓名-->
        <reportDoctorName>exentric</reportDoctorName>
    </reportAuthor>
    <!--報告科別代碼-->
    <reportDepartmentId>00</reportDepartmentId>
    <!--報告科別名稱-->
    <reportDepartmentName>不分科</reportDepartmentName>
    <!--報告日期-->
    <reportDate>20240701050837</reportDate>
    <!--就醫編號-->
    <caseNo>12345678100301</caseNo>
    <!--就醫時間-->
    <caseTime>20240601</caseTime>
    <!--排序號碼-->
    <sortNo>排序號碼</sortNo>
    <!--延伸欄位1-->
    <extension1>延伸欄位1</extension1>
    <!--延伸欄位2-->
    <extension2>延伸欄位2</extension2>
    <!--延伸欄位3-->
    <extension3>延伸欄位3</extension3>
    <!--延伸欄位4-->
    <extension4>延伸欄位4</extension4>
    <!--延伸欄位5-->
    <extension5>延伸欄位5</extension5>
    <!--機密等級-->
    <secretLv>0</secretLv>
    <!--流水號-->
    <serialNumber>流水號</serialNumber>
    <!--機密碼-->
    <confidentialityCode>機密碼</confidentialityCode>
    <!--醫療院所OID-->
    <hospitalOID>醫療院所OID</hospitalOID>
    <!--身份證號種類-->
    <patientIdType>身份證號種類</patientIdType>
    <!--採檢日期時間-->
    <samplingDate>採檢日期時間</samplingDate>
    <!--LOINC Code-->
    <code>LOINC Code</code>
    <!--LOINC Name-->
    <name>LOINC Name</name>
    <!--檢驗技術人員-->
    <inspectors>
        <!--檢驗技術師代碼-->
        <inspectionUserId>檢驗技術師代碼</inspectionUserId>
        <!--檢驗技術師姓名-->
        <inspectionUserName>檢驗技術師姓名</inspectionUserName>
        <!--檢驗日期時間-->
        <inspectionDate>檢驗日期時間</inspectionDate>
    </inspectors>
    <!--檢驗技術人員-->
    <inspectors>
        <!--檢驗技術師代碼-->
        <inspectionUserId>檢驗技術師代碼</inspectionUserId>
        <!--檢驗技術師姓名-->
        <inspectionUserName>檢驗技術師姓名</inspectionUserName>
        <!--檢驗日期時間-->
        <inspectionDate>檢驗日期時間</inspectionDate>
    </inspectors>
    <!--檢驗技術人員-->
    <inspectors>
        <!--檢驗技術師代碼-->
        <inspectionUserId>檢驗技術師代碼</inspectionUserId>
        <!--檢驗技術師姓名-->
        <inspectionUserName>檢驗技術師姓名</inspectionUserName>
        <!--檢驗日期時間-->
        <inspectionDate>檢驗日期時間</inspectionDate>
    </inspectors>
    <!--檢驗結果-->
    <testResults>
        <!--健保檢驗項目代號-->
        <nhiTestCode>健保檢驗項目代號</nhiTestCode>
        <!--健保檢驗項目名稱-->
        <nhiTestName>健保檢驗項目名稱</nhiTestName>
        <!--健保檢驗項目Lonic代碼-->
        <nhiTestLogicCode>健保檢驗項目Lonic代碼</nhiTestLogicCode>
        <!--健保檢驗項目Lonic名稱-->
        <nhiTestLogicName>健保檢驗項目Lonic名稱</nhiTestLogicName>
        <!--收件日期時間-->
        <deliveringDate>收件日期時間</deliveringDate>
        <!--檢體類別代碼-->
        <samplingCategoriesCode>檢體類別代碼</samplingCategoriesCode>
        <!--檢體類別名稱-->
        <samplingCategoriesName>檢體類別名稱</samplingCategoriesName>
        <!--檢體類別說明-->
        <samplingCategoriesDesc>檢體類別說明</samplingCategoriesDesc>
        <!--檢體來源-->
        <samplingSource>檢體來源</samplingSource>
        <!--檢驗項目項次-->
        <itemNo>檢驗項目項次</itemNo>
        <!--檢驗項目Loinc代碼-->
        <loincCode>檢驗項目Loinc代碼</loincCode>
        <!--檢驗項目Loinc名稱-->
        <loincName>檢驗項目Loinc名稱</loincName>
        <!--檢驗值-->
        <value>檢驗值</value>
        <!--參考值Low-->
        <low>參考值Low</low>
        <!--參考值High-->
        <high>參考值High</high>
        <!--單位-->
        <unit>單位</unit>
        <!--備註-->
        <remark>備註</remark>
        <!--檢驗方法代碼-->
        <methodCode>檢驗方法代碼</methodCode>
        <!--檢驗方法名稱-->
        <methodName>檢驗方法名稱</methodName>
        <!--報告日期時間-->
        <reportDate>20240701050837</reportDate>
    </testResults>
    <!--檢驗結果-->
    <testResults>
        <!--健保檢驗項目代號-->
        <nhiTestCode>健保檢驗項目代號</nhiTestCode>
        <!--健保檢驗項目名稱-->
        <nhiTestName>健保檢驗項目名稱</nhiTestName>
        <!--健保檢驗項目Lonic代碼-->
        <nhiTestLogicCode>健保檢驗項目Lonic代碼</nhiTestLogicCode>
        <!--健保檢驗項目Lonic名稱-->
        <nhiTestLogicName>健保檢驗項目Lonic名稱</nhiTestLogicName>
        <!--收件日期時間-->
        <deliveringDate>收件日期時間</deliveringDate>
        <!--檢體類別代碼-->
        <samplingCategoriesCode>檢體類別代碼</samplingCategoriesCode>
        <!--檢體類別名稱-->
        <samplingCategoriesName>檢體類別名稱</samplingCategoriesName>
        <!--檢體類別說明-->
        <samplingCategoriesDesc>檢體類別說明</samplingCategoriesDesc>
        <!--檢體來源-->
        <samplingSource>檢體來源</samplingSource>
        <!--檢驗項目項次-->
        <itemNo>檢驗項目項次</itemNo>
        <!--檢驗項目Loinc代碼-->
        <loincCode>檢驗項目Loinc代碼</loincCode>
        <!--檢驗項目Loinc名稱-->
        <loincName>檢驗項目Loinc名稱</loincName>
        <!--檢驗值-->
        <value>檢驗值</value>
        <!--參考值Low-->
        <low>參考值Low</low>
        <!--參考值High-->
        <high>參考值High</high>
        <!--單位-->
        <unit>單位</unit>
        <!--備註-->
        <remark>備註</remark>
        <!--檢驗方法代碼-->
        <methodCode>檢驗方法代碼</methodCode>
        <!--檢驗方法名稱-->
        <methodName>檢驗方法名稱</methodName>
        <!--報告日期時間-->
        <reportDate>20240701050837</reportDate>
    </testResults>
    <!--檢驗結果-->
    <testResults>
        <!--健保檢驗項目代號-->
        <nhiTestCode>健保檢驗項目代號</nhiTestCode>
        <!--健保檢驗項目名稱-->
        <nhiTestName>健保檢驗項目名稱</nhiTestName>
        <!--健保檢驗項目Lonic代碼-->
        <nhiTestLogicCode>健保檢驗項目Lonic代碼</nhiTestLogicCode>
        <!--健保檢驗項目Lonic名稱-->
        <nhiTestLogicName>健保檢驗項目Lonic名稱</nhiTestLogicName>
        <!--收件日期時間-->
        <deliveringDate>收件日期時間</deliveringDate>
        <!--檢體類別代碼-->
        <samplingCategoriesCode>檢體類別代碼</samplingCategoriesCode>
        <!--檢體類別名稱-->
        <samplingCategoriesName>檢體類別名稱</samplingCategoriesName>
        <!--檢體類別說明-->
        <samplingCategoriesDesc>檢體類別說明</samplingCategoriesDesc>
        <!--檢體來源-->
        <samplingSource>檢體來源</samplingSource>
        <!--檢驗項目項次-->
        <itemNo>檢驗項目項次</itemNo>
        <!--檢驗項目Loinc代碼-->
        <loincCode>檢驗項目Loinc代碼</loincCode>
        <!--檢驗項目Loinc名稱-->
        <loincName>檢驗項目Loinc名稱</loincName>
        <!--檢驗值-->
        <value>檢驗值</value>
        <!--參考值Low-->
        <low>參考值Low</low>
        <!--參考值High-->
        <high>參考值High</high>
        <!--單位-->
        <unit>單位</unit>
        <!--備註-->
        <remark>備註</remark>
        <!--檢驗方法代碼-->
        <methodCode>檢驗方法代碼</methodCode>
        <!--檢驗方法名稱-->
        <methodName>檢驗方法名稱</methodName>
        <!--報告日期時間-->
        <reportDate>20240701050837</reportDate>
    </testResults>
    <!--註記1-->
    <LAB_Memo>註記1</LAB_Memo>
</xDocument>
